arraydebug/__init__.py
arraydebug/array_like.py
arraydebug/core.py
arraydebug/numpy.py
arraydebug/torch.py
arraydebug-0.1.2.dist-info/AUTHORS.md
arraydebug-0.1.2.dist-info/LICENSE
arraydebug-0.1.2.dist-info/METADATA
arraydebug-0.1.2.dist-info/WHEEL
arraydebug-0.1.2.dist-info/top_level.txt
arraydebug-0.1.2.dist-info/zip-safe
arraydebug-0.1.2.dist-info/RECORD
