Metadata-Version: 2.1
Name: arraydebug
Version: 0.1.2
Summary: ArrayDebug generates human-friendly debug information for array-like objects.
Home-page: https://github.com/liqimai/arraydebug
Author: Qimai Li
Author-email: liqimai@qq.com
License: MIT license
Project-URL: Bug Tracker, https://github.com/liqimai/arraydebug/issues
Keywords: arraydebug
Platform: UNKNOWN
Classifier: Development Status :: 2 - Pre-Alpha
Classifier: Intended Audience :: Developers
Classifier: License :: OSI Approved :: MIT License
Classifier: Natural Language :: English
Classifier: Operating System :: OS Independent
Classifier: Programming Language :: Python :: 3
Classifier: Programming Language :: Python :: 3.6
Classifier: Programming Language :: Python :: 3.7
Classifier: Programming Language :: Python :: 3.8
Classifier: Programming Language :: Python :: 3.9
Classifier: Programming Language :: Python :: 3.10
Requires-Python: >=3.6
License-File: LICENSE
License-File: AUTHORS.md
Requires-Dist: numpy
